{"cameraMode":{"drawMode":0,"name":"Shaded","section":"Shading Mode"},"sceneLighting":true,"audioPlay":false,"sceneViewState":{"m_AlwaysRefresh":false,"showFog":true,"showSkybox":true,"showFlares":true,"showImageEffects":true,"showParticleSystems":true,"showVisualEffectGraphs":true,"m_FxEnabled":true},"in2DMode":false,"pivot":{"x":-28.541976928710939,"y":-29.530824661254884,"z":33.192298889160159},"rotation":{"x":-0.43500834703445437,"y":-0.40672922134399416,"z":0.22983787953853608,"w":-0.7701385617256165},"size":46.71714401245117,"orthographic":false}